project_checks/__init__.py
project_checks/management/__init__.py
project_checks/management/commands/__init__.py
project_checks/management/commands/base.py
project_checks/templates/project_checks/django_url.txt
django_project_checks-0.5.0.dist-info/METADATA
django_project_checks-0.5.0.dist-info/WHEEL
django_project_checks-0.5.0.dist-info/licenses/LICENSE
django_project_checks-0.5.0.dist-info/RECORD
